llmpop/__init__.py
llmpop/init_llm.py
llmpop/monitor_resources.py
llmpop/py.typed
llmpop/version.py
llmpop-0.4.0.dist-info/licenses/LICENSE
llmpop-0.4.0.dist-info/METADATA
llmpop-0.4.0.dist-info/WHEEL
llmpop-0.4.0.dist-info/top_level.txt
llmpop-0.4.0.dist-info/RECORD
