Metadata-Version: 2.4
Name: llmpop
Version: 0.4.0
Summary: The Python library that lets you spin up any LLM with a single function. Route between local and remote LLMs with a unified interface.
Author: Lior Gazit
License: MIT
Project-URL: Homepage, https://github.com/LiorGazit/llmpop
Project-URL: Issues, https://github.com/LiorGazit/llmpop/issues
Keywords: LLM,Ollama,LangChain,Agents,OpenAI,Router
Classifier: Programming Language :: Python :: 3
Classifier: License :: OSI Approved :: MIT License
Classifier: Operating System :: MacOS :: MacOS X
Classifier: Operating System :: POSIX :: Linux
Requires-Python: >=3.9
License-File: LICENSE
Requires-Dist: requests>=2.31.0
Requires-Dist: psutil>=5.9.0
Requires-Dist: langchain-core>=0.2.0
Requires-Dist: langchain-ollama>=0.1.0
Provides-Extra: openai
Requires-Dist: langchain-openai>=0.2.0; extra == "openai"
Provides-Extra: dev
Requires-Dist: pytest>=7.4; extra == "dev"
Requires-Dist: pytest-cov>=4.1; extra == "dev"
Requires-Dist: ruff>=0.5; extra == "dev"
Requires-Dist: black>=24.8.0; extra == "dev"
Requires-Dist: mypy>=1.10.0; extra == "dev"
Requires-Dist: pre-commit>=3.7.0; extra == "dev"
Dynamic: license-file
